pyriddle/__init__.py
pyriddle/cli.py
pyriddle/data.py
pyriddle/riddle.py
pyriddle-1.0.0.dist-info/LICENSE
pyriddle-1.0.0.dist-info/METADATA
pyriddle-1.0.0.dist-info/WHEEL
pyriddle-1.0.0.dist-info/entry_points.txt
pyriddle-1.0.0.dist-info/top_level.txt
pyriddle-1.0.0.dist-info/RECORD
